haralick_torch/__init__.py
haralick_torch/cli.py
haralick_torch/core.py
haralick_torch/io.py
haralick_torch/pca.py
haralick_torch/tiles.py
haralick_torch-1.1.0.dist-info/licenses/LICENSE
haralick_torch-1.1.0.dist-info/METADATA
haralick_torch-1.1.0.dist-info/WHEEL
haralick_torch-1.1.0.dist-info/entry_points.txt
haralick_torch-1.1.0.dist-info/top_level.txt
haralick_torch-1.1.0.dist-info/RECORD
