Metadata-Version: 2.4
Name: haralick-torch
Version: 1.1.0
Summary: GPU-accelerated Haralick texture extraction for GeoTIFFs
Requires-Python: >=3.9
License-File: LICENSE
Requires-Dist: torch
Requires-Dist: numpy
Provides-Extra: gdal
Requires-Dist: gdal; extra == "gdal"
Dynamic: license-file
